ultra_pass_sidecar/__init__.py
ultra_pass_sidecar/auth_service.py
ultra_pass_sidecar/cli.py
ultra_pass_sidecar/publish.py
ultra_pass_sidecar-0.0.42.dist-info/METADATA
ultra_pass_sidecar-0.0.42.dist-info/WHEEL
ultra_pass_sidecar-0.0.42.dist-info/entry_points.txt
ultra_pass_sidecar-0.0.42.dist-info/top_level.txt
ultra_pass_sidecar-0.0.42.dist-info/RECORD
