Metadata-Version: 2.4
Name: ultra-pass-sidecar
Version: 0.0.42
Summary: 一个简洁的Python微服务sidecar，支持自动注册到Nacos和Feign风格调用，支持配置中心，支持权限，资源管理
Home-page: https://github.com/yourusername/ultra-pass-py-sidecar
Author: Luozhiguo
Author-email: luozhiguo@example.com
License: MIT
Project-URL: Bug Reports, https://github.com/yourusername/ultra-pass-py-sidecar/issues
Project-URL: Source, https://github.com/yourusername/ultra-pass-py-sidecar
Project-URL: Documentation, https://github.com/yourusername/ultra-pass-py-sidecar#readme
Keywords: microservice,sidecar,nacos,service-discovery,feign,flask,fastapi,async,http-client,configuration
Classifier: Development Status :: 4 - Beta
Classifier: Intended Audience :: Developers
Classifier: License :: OSI Approved :: MIT License
Classifier: Operating System :: OS Independent
Classifier: Programming Language :: Python :: 3
Classifier: Programming Language :: Python :: 3.8
Classifier: Programming Language :: Python :: 3.9
Classifier: Programming Language :: Python :: 3.10
Classifier: Programming Language :: Python :: 3.11
Classifier: Programming Language :: Python :: 3.12
Classifier: Topic :: Software Development :: Libraries :: Python Modules
Classifier: Topic :: Internet :: WWW/HTTP :: HTTP Servers
Classifier: Topic :: System :: Distributed Computing
Classifier: Framework :: Flask
Classifier: Framework :: FastAPI
Requires-Python: >=3.8
Requires-Dist: flask<3.0.0,>=2.0.0
Requires-Dist: flask-cors<5.0.0,>=3.0.0
Requires-Dist: requests<3.0.0,>=2.5.0
Requires-Dist: pyyaml<7.0.0,>=5.1
Requires-Dist: python-dotenv<1.0.0,>=0.19.0
Requires-Dist: aiohttp<4.0.0,>=3.8.0
Requires-Dist: nacos-sdk-python<1.0.0,>=0.1.12
Requires-Dist: fastapi<1.0.0,>=0.68.0
Requires-Dist: uvicorn<1.0.0,>=0.15.0
Requires-Dist: starlette<1.0.0,>=0.14.0
Requires-Dist: pydantic<2.0.0,>=1.8.0
Requires-Dist: django<4.0.0,>=3.2.0
Requires-Dist: asyncio-mqtt<1.0.0,>=0.11.0
Requires-Dist: aiofiles<1.0.0,>=0.8.0
Requires-Dist: websockets<11.0.0,>=10.0
Requires-Dist: httpx<1.0.0,>=0.24.0
Requires-Dist: marshmallow<4.0.0,>=3.14.0
Requires-Dist: jsonschema<5.0.0,>=4.0.0
Requires-Dist: urllib3<2.0.0,>=1.26.0
Requires-Dist: structlog<22.0.0,>=21.5.0
Requires-Dist: prometheus-client<1.0.0,>=0.14.0
Requires-Dist: sqlalchemy<2.0.0,>=1.4.0
Requires-Dist: alembic<2.0.0,>=1.7.0
Requires-Dist: redis<5.0.0,>=4.0.0
Requires-Dist: cryptography<4.0.0,>=3.4.0
Requires-Dist: PyJWT<3.0.0,>=2.0.0
Requires-Dist: bcrypt<4.0.0,>=3.2.0
Requires-Dist: click<9.0.0,>=8.0.0
Requires-Dist: rich<13.0.0,>=12.0.0
Requires-Dist: typer<1.0.0,>=0.4.0
Provides-Extra: dev
Requires-Dist: pytest>=6.0; extra == "dev"
Requires-Dist: pytest-asyncio>=0.18.0; extra == "dev"
Requires-Dist: pytest-cov>=3.0.0; extra == "dev"
Requires-Dist: pytest-mock>=3.6.0; extra == "dev"
Requires-Dist: black>=22.0; extra == "dev"
Requires-Dist: flake8>=4.0; extra == "dev"
Requires-Dist: mypy>=0.950; extra == "dev"
Requires-Dist: isort>=5.10.0; extra == "dev"
Requires-Dist: pre-commit>=2.17.0; extra == "dev"
Provides-Extra: test
Requires-Dist: pytest>=6.0; extra == "test"
Requires-Dist: pytest-asyncio>=0.18.0; extra == "test"
Requires-Dist: pytest-cov>=3.0.0; extra == "test"
Requires-Dist: pytest-mock>=3.6.0; extra == "test"
Requires-Dist: responses>=0.20.0; extra == "test"
Requires-Dist: httpx>=0.24.0; extra == "test"
Provides-Extra: docs
Requires-Dist: sphinx>=4.0.0; extra == "docs"
Requires-Dist: sphinx-rtd-theme>=1.0.0; extra == "docs"
Requires-Dist: myst-parser>=0.17.0; extra == "docs"
Provides-Extra: all
Requires-Dist: fastapi>=0.68.0; extra == "all"
Requires-Dist: uvicorn>=0.15.0; extra == "all"
Requires-Dist: starlette>=0.14.0; extra == "all"
Requires-Dist: pydantic>=1.8.0; extra == "all"
Requires-Dist: asyncio-mqtt>=0.11.0; extra == "all"
Requires-Dist: aiofiles>=0.8.0; extra == "all"
Requires-Dist: python-dotenv>=0.19.0; extra == "all"
Requires-Dist: marshmallow>=3.14.0; extra == "all"
Requires-Dist: jsonschema>=4.0.0; extra == "all"
Requires-Dist: httpx>=0.24.0; extra == "all"
Requires-Dist: websockets>=10.0; extra == "all"
Requires-Dist: urllib3>=1.26.0; extra == "all"
Requires-Dist: structlog>=21.5.0; extra == "all"
Requires-Dist: prometheus-client>=0.14.0; extra == "all"
Requires-Dist: sqlalchemy>=1.4.0; extra == "all"
Requires-Dist: alembic>=1.7.0; extra == "all"
Requires-Dist: redis>=4.0.0; extra == "all"
Requires-Dist: cryptography>=3.4.0; extra == "all"
Requires-Dist: jwt>=1.3.1; extra == "all"
Requires-Dist: bcrypt>=3.2.0; extra == "all"
Requires-Dist: click>=8.0.0; extra == "all"
Requires-Dist: rich>=12.0.0; extra == "all"
Requires-Dist: typer>=0.4.0; extra == "all"
Requires-Dist: pydantic-settings>=2.0.0; extra == "all"
Dynamic: author
Dynamic: author-email
Dynamic: classifier
Dynamic: description
Dynamic: description-content-type
Dynamic: home-page
Dynamic: keywords
Dynamic: license
Dynamic: project-url
Dynamic: provides-extra
Dynamic: requires-dist
Dynamic: requires-python
Dynamic: summary
